[
    {
        "config_skill_key": "2000",
        "#hero_name": "UnderDog",
        "config_hero_key": "1000",
        "skill_name": "Star Fall",
        "skill_cast_type": "NoneTarget",
        "skill_icon": null,
        "skill_prefab_path": "SkillPrefabs/Piercing Vine.prefab",
        "description": "Calls down celestial stars, dealing AoE damage to all enemies in a large radius"
    },
    {
        "config_skill_key": "2001",
        "#hero_name": "UnderDog",
        "config_hero_key": "1000",
        "skill_name": "Arrow",
        "skill_cast_type": "Direction",
        "skill_icon": null,
        "skill_prefab_path": null,
        "description": "Fires a long-range, magical arrow in a straight line, stunning and damaging the first enemy it hits"
    }
]